README.md
setup.py
cathodedataextractor/__init__.py
cathodedataextractor/information_extraction_pipe.py
cathodedataextractor/relationextractpostprocessing.py
cathodedataextractor/utils.py
cathodedataextractor.egg-info/PKG-INFO
cathodedataextractor.egg-info/SOURCES.txt
cathodedataextractor.egg-info/dependency_links.txt
cathodedataextractor.egg-info/requires.txt
cathodedataextractor.egg-info/top_level.txt
cathodedataextractor/cathodetext2chem/__init__.py
cathodedataextractor/cathodetext2chem/parser_pipeline.py
cathodedataextractor/cathodetext2chem/regex_parser.py
cathodedataextractor/nlp/__init__.py
cathodedataextractor/nlp/abbrev.py
cathodedataextractor/nlp/cdetext.py
cathodedataextractor/nlp/cner.py
cathodedataextractor/nlp/modi_cde_nlp.py
cathodedataextractor/nlp/tokenizer4units.py
cathodedataextractor/parse/__init__.py
cathodedataextractor/parse/crc_relation.py
cathodedataextractor/parse/regex_functions.py
cathodedataextractor/parse/regex_pattern.py
cathodedataextractor/parse/relation_extraction.py
cathodedataextractor/text/__init__.py
cathodedataextractor/text/paragraph_classification.py
cathodedataextractor/text/sibs_process.py
tests/__init__.py
tests/test_cathodetext2chem.py
tests/test_nlp_abbr.py
tests/test_nlp_cner.py
tests/test_nlp_tokenize.py
tests/test_nlp_unitstokenizer.py
tests/test_parse.py
tests/test_text2chem.py
tests/test_text2chem_parser.py
tests/test_text_process.py
tests/resources/__init__.py