Metadata-Version: 2.1
Name: cathodedataextractor
Version: 0.0.4
Summary: A document-level information extraction pipeline for layered cathode materials for sodium-ion batteries.
Home-page: https://github.com/GGNoWayBack/cathodedataextractor
Author: Yuxiao Gou
Author-email: gouyx@mail2.sysu.edu.cn
License: MIT
Keywords: text-mining information-extraction nlp battery-information
Platform: UNKNOWN
Classifier: Intended Audience :: Developers
Classifier: Intended Audience :: Science/Research
Classifier: License :: OSI Approved :: MIT License
Classifier: Operating System :: OS Independent
Classifier: Programming Language :: Python :: 3.6
Classifier: Programming Language :: Python :: 3.7
Classifier: Topic :: Scientific/Engineering
Classifier: Topic :: Text Processing
